eflips/model/__init__.py
eflips/model/alembic.ini
eflips/model/depot.py
eflips/model/general.py
eflips/model/migrations/env.py
eflips/model/migrations/script.py.mako
eflips/model/migrations/versions/0548463664b4_3_1_0.py
eflips/model/migrations/versions/0820463fc0aa_6_0_5.py
eflips/model/migrations/versions/126892076499_v2_0_0.py
eflips/model/migrations/versions/1d0f22ea5789_5_0_0.py
eflips/model/migrations/versions/1d60ee839397_6_0_7.py
eflips/model/migrations/versions/26166d1bc557_6_0_4.py
eflips/model/migrations/versions/37ece7aa1742_6_0_0.py
eflips/model/migrations/versions/3a62f62ef264_v10_0_0.py
eflips/model/migrations/versions/3ed40e170361_5_1_0.py
eflips/model/migrations/versions/6ac022147397_3_0_0.py
eflips/model/migrations/versions/6e96cbfb3523_v10_0_0.py
eflips/model/migrations/versions/747085e84b69_6_0_8.py
eflips/model/migrations/versions/7483339ae654_v2_2_0.py
eflips/model/migrations/versions/7c26ba933d67_7_0_2.py
eflips/model/migrations/versions/801705905f79_8_0_0.py
eflips/model/migrations/versions/82b5c4d01e66_5_2_0.py
eflips/model/migrations/versions/86302241f50a_5_1_3.py
eflips/model/migrations/versions/8755e7591dcd_7_0_1.py
eflips/model/migrations/versions/8c6c0d114d0c_4_0_0.py
eflips/model/migrations/versions/8f2835b87d6e_v9_0_1.py
eflips/model/migrations/versions/921afffb2adf_v10_0_2.py
eflips/model/migrations/versions/9415968f804e_6_0_6.py
eflips/model/migrations/versions/986abf14da65_5_1_7.py
eflips/model/migrations/versions/9e29124f8ce6_v1_1_6.py
eflips/model/migrations/versions/a06c97c98d2c_v2_1_0.py
eflips/model/migrations/versions/a9f1c33488b6_3_0_0.py
eflips/model/migrations/versions/baef3598b52c_v2_3_0.py
eflips/model/migrations/versions/ddb65b675e43_9_0_0.py
eflips/model/migrations/versions/e232e88e379d_5_1_2.py
eflips/model/migrations/versions/e85326ec1582_5_1_1.py
eflips/model/migrations/versions/e8f748c14b93_8_1_0.py
eflips/model/migrations/versions/ee9340feec83_5_3_0.py
eflips/model/network.py
eflips/model/py.typed
eflips_model-10.0.3.dist-info/METADATA
eflips_model-10.0.3.dist-info/WHEEL
eflips_model-10.0.3.dist-info/licenses/LICENSE.md
eflips_model-10.0.3.dist-info/RECORD
