Metadata-Version: 2.4
Name: eflips-model
Version: 10.0.3
Summary: A common data model for the eflips family of electric vehicle simulation & optimization tools.
License: AGPL-3.0-or-later
License-File: LICENSE.md
Author: Ludger Heide
Author-email: ludger.heide@tu-berlin.de
Requires-Python: >=3.10,<4.0
Classifier: License :: OSI Approved :: GNU Affero General Public License v3 or later (AGPLv3+)
Classifier: Programming Language :: Python :: 3
Classifier: Programming Language :: Python :: 3.10
Classifier: Programming Language :: Python :: 3.11
Classifier: Programming Language :: Python :: 3.12
Classifier: Programming Language :: Python :: 3.13
Classifier: Programming Language :: Python :: 3.14
Requires-Dist: alembic (>=1.12.1,<2.0.0)
Requires-Dist: geoalchemy2 (>=0.14.2,<0.15.0)
Requires-Dist: numpy (>=2.2.0,<3.0.0)
Requires-Dist: pandas (>=2.2.0,<3.0.0)
Requires-Dist: psycopg2-binary (>=2.9.10,<3.0.0)
Requires-Dist: pyproj (>=3.7.1,<4.0.0)
Requires-Dist: shapely (>=2.1.0,<3.0.0)
Requires-Dist: sqlalchemy (>=2.0.23,<3.0.0)
Project-URL: Homepage, https://github.com/mpm-tu-berlin/eflips-model
Project-URL: Repository, https://github.com/mpm-tu-berlin/eflips-model
